stock_csv/__init__.py
stock_csv/downloader.py
stock_downloader-0.4.dist-info/LICENSE
stock_downloader-0.4.dist-info/METADATA
stock_downloader-0.4.dist-info/WHEEL
stock_downloader-0.4.dist-info/top_level.txt
stock_downloader-0.4.dist-info/RECORD
