Metadata-Version: 2.1
Name: stock-downloader
Version: 0.4
Author: Adam Sierakowski
License-File: LICENSE
Requires-Dist: yfinance
